{
  "name": "Millie Waters",
  "age": 64,
  "address": {
    "street": "Cidro Parkway",
    "city": "Hutazda",
    "state": "NV",
    "zip": "88173"
  },
  "contact": {
    "phone": "(670) 309-6593",
    "servicePhone": "800934642"
  },
  "birthday": "1993-08-06T05:14:46.745Z",
  "ip": "70.19.32.30",
  "foo": "bar",
  "profile": {
    "about": "Te jel saumovu fowzemli gakes kowvucvu goru goz dut avo vuba fef volnewij rar ruzbuzozo lut. Todum ucivo te jesi ralnof wegedso vijeni vijaz novid nuwnine emjira di pa. Ese ki sa zubluzo it cuzon lukofiru molop evvehe uco izibin tugec hiconro ve muspu fepa. Bob ikbawu ovaime sap vowuwre kah on la ideehlo guug luc cij co jazrelti dajobwa cache. Keccag vizlec netifi hupkervo cilez tub ejezolte tutma wo dimagu hop kar uvnoj joadahal zetlu. Dengeguc vof buti nipiz duc ibi vowar ebaodogi itcas favauc tubluc nir los. Ewulohaz mud damet caha wo ihbo wuc dowfizumu ugceefa nib guvekluh mirlo.",
    "bio": "Za usu etduj vubce suprif piwtihve zubehbe jizsut voip curcena uklag ve hodpe tad. Doszot julofa pir co vul urpezoj saazu kohemec ruris put nub womef ve tebodi tembihu. Eb kigjan vinu loce ne irisotu cez wev ehabo ohisisuzi gu gohu icuhi zom."
  },
  "apiKey": "b0f61853bc30eb6ff022f3d97925e6cf325cffcb0b970e9e1631c1784b8248e4",
  "currency": {
    "code": "ALL",
    "name": "Albania Lek"
  }
}