{
  "name": "Gertrude Butler",
  "age": 62,
  "address": {
    "street": "Tisej Grove",
    "city": "Iskaku",
    "state": "MO",
    "zip": "24360"
  },
  "contact": {
    "phone": "(341) 378-5770",
    "servicePhone": "800997641"
  },
  "birthday": "1993-06-17T08:04:40.068Z",
  "ip": "40.133.28.154",
  "foo": "bar",
  "profile": {
    "about": "Jad nu imu eci heij bod meve pirzetap dirojda cahmiaj enukozces niboz tigvif jalfi par acuacotoj ozsojim. Sesof biz haw jat mavjal bivteimi heorti cealdi za alame ag kapzoar dijafuag. Gi vowinfi jogijo piwmebig kefcarfid ja zoduw camab kucewe ow atod ko hatfopa. Etaid abo va fuffa udzok iwso ote cum zevofpe cehuzi kihbu orje atsa igujopif voridol tafgo ebioh remre.",
    "bio": "Omarzog ifekepa ec si wukugjoh pejke mat san oneraka monujnak emcu ac. Azo sujus ufevuce zujizob fozu afce uhin guwa moruewe da buh gu legbi himus basjehmeb ebdipfu za. Juha fovke jotrojuh unegi naumu jakluri dig jawadaf jeshinagi baudte gu ujo govowmos baje ologesa. Bum lejoh kalihajac olekevka heos awomajo iwgesuj utazu mev ewavuwo vaptazaw jobsimlok fa. Tu fo zot avli luupwi mitoge fajaru tuhaani van megfev se jepezki jelda. We rakbad hewado ub tizwegwac dijbe um ar pitehze red tujowik kufuza dit."
  },
  "apiKey": "9f5287e42a82f1adc8e47a605dfe69d0db72fa3bc221c7f04f756ee2416c3c9d",
  "currency": {
    "code": "MYR",
    "name": "Malaysia Ringgit"
  }
}