{
  "name": "Nettie Pierce",
  "age": 39,
  "address": {
    "street": "Gogpok Extension",
    "city": "Bewazbo",
    "state": "KY",
    "zip": "63869"
  },
  "contact": {
    "phone": "(723) 555-3895",
    "servicePhone": "800876445"
  },
  "birthday": "1963-05-16T03:36:34.667Z",
  "ip": "191.39.99.146",
  "foo": "bar",
  "profile": {
    "about": "Re gepreh asuji mivven kiheve jilbuvi rikazke duwva wiepejam nucun roittec tu dudobzaf. Acepeit dedokuha zav bimurwom kokagpal jufo wuhedpa libajat dobapcec ef jebpur mi fitci. Bu un ribmerhim go ref zanekhi gufoop hosuzjo dobepgap ozobehac wudnu korip ne nabalna.",
    "bio": "Relnug muewoze uwu udiebi egbik tijvah keavoko so gambag ri vidhislod awako nah. Futaszu ralma gambo olu gagohu pihag asulizmob tub zozeniuf abdeb odecoze dabne so fipvu vik. Sike jumjehel ja jul muzzoghuk epaigo cowez efo zucug hojikim vo ajru sidete pugampo efu za movdag si. Hi toki cepkevaju wu omvuctiv da vogu ujiathid ludfanfu jima emanoora bavwasad mitcumu zus tawazav fu pehpobivu afevikgem. Verza apoulu div zerogaip odzouto cobenic wefdo sumocdil udeege tiffiv sucohwu wak zemwotef lasi gofse da nujika poju. Fu nauso nobva gijneuto esedebe fu ohoecheb janhudlud da umaze ti japigif gi lumza ka joz. Hohnekeg wav lemunjuh mo hilguru sef owoleg haopkib sukwu kag wimmi zieso ecnawig ohzis romvobre bunri."
  },
  "apiKey": "12374a8fccb8e17c7fc672c49ae605b4344f026f25dd4bc2a04267cbfa712e00",
  "currency": {
    "code": "MWK",
    "name": "Malawi Kwacha"
  }
}