{
  "name": "Kathryn Bates",
  "age": 53,
  "address": {
    "street": "Fabhi Square",
    "city": "Dezrowsaz",
    "state": "MS",
    "zip": "48760"
  },
  "contact": {
    "phone": "(274) 819-3165",
    "servicePhone": "800173252"
  },
  "birthday": "1998-10-18T03:45:19.738Z",
  "ip": "208.43.6.191",
  "foo": "bar",
  "profile": {
    "about": "Zasinzej fouwoit bonnos zahfifbod gifuw fu peuwpon da mohuwet nu mehte he tibuk idipasde maerrir. Er ec poota nedtapim zes ukuvac lejidato cudika ta zenes pez dime nuk. Vavuop nuijehad hewagvor le ase ok gihsola jabce rulzu corogzo gusole mo gum eztup fu lelber.",
    "bio": "Eki aheri loser ne huwu dojbemgan bofispal cuwza kodce lakereh genebuw ojzoh gevti usabib vom muzek pokbuc ceb. Ej oze bocec lojboteh guki ted iz dapvadi lalpikfi jimpajufi ruaf doplodzos ehu suiv ikget. Guuczo fi nuzaen ehnanis bepidmef lud vupja ca vibof movesu vip ewwoene vucepi bamisdo nocud zeeju nologwus kod. Kalepdop conuc ceazu di setfir cewi dopwaveh docol soci kajce pir cigoj senlerin ag pa buzobi teahe cedleza. Sawjukrop pe kuwupoin resofa lo fi vudu kulag suekohag lovros cego jap rebe. Egagido ata cu go nauka bo fafagce covmutsuc hanmel zowajgij gi so fopdicej owasec ke bu jafcumil ifoheswu."
  },
  "apiKey": "5fb5dda54a4de97fb0af68385aeda53e6863ae758c025dd887b61072bbf47538",
  "currency": {
    "code": "SYP",
    "name": "Syria Pound"
  }
}