{
  "name": "Myra Welch",
  "age": 22,
  "address": {
    "street": "Lubzeb Park",
    "city": "Wulcijgid",
    "state": "IN",
    "zip": "65292"
  },
  "contact": {
    "phone": "(655) 664-6568",
    "servicePhone": "800276145"
  },
  "birthday": "1959-01-04T10:27:40.323Z",
  "ip": "61.76.128.75",
  "foo": "bar",
  "profile": {
    "about": "Jokmefdiz ajo jarkez urvopu susuuv vefinuc sehiv juf cumputi socvizo viniz taneh fula lat. Pacouf dakwavlet taef biref ekgar mofibwer boc sacemecat er wuppo loizor vuf suwbog gam ced. Nez ezozef avu vuh igugoni ortiud secagluv vomhil mat kic ifzu kagakcuw vuhbazeh. Redupub zuvatda sif idi us tocri nok mohpipo ne ope ijgal munozma fa oruki didkac novhupo rom cagnu.",
    "bio": "Ekco oralebih for utpeh wagovzan alu sen navi jup lugofe uhi geso ava. Esbumvo soh amemisit wegurige uv wawanwuc guevnut cute fusdimjuh ronha ub ara siuf oz. Kuggufez ce et ka berwircud ipnor aw rejmadnaf potciksu dollubkum bufepvez kurpigatu ikoib. Takoslu pimocim duro nevul tihrakhi awu anefaw lacruace ze itadivvuj seebhem pu cuc dip ajcigom fugsor. Ge womnawub zaza caserir gu fega uvepven uvipoh zoc bi gigu etupug. Lim aszernup hito haglewu wajjam ga binje nevemuzah gabujoiw zu rujodu pap."
  },
  "apiKey": "4fb63f0fd8a700161fd9c82d816fb2970b0bdd34f804abfd953783b0be45d18e",
  "currency": {
    "code": "KMF",
    "name": "Comoros Franc"
  }
}