{
  "name": "Essie Medina",
  "age": 47,
  "address": {
    "street": "Sunu Place",
    "city": "Irtuwdi",
    "state": "AZ",
    "zip": "49719"
  },
  "contact": {
    "phone": "(541) 346-7393",
    "servicePhone": "800399228"
  },
  "birthday": "1979-03-29T01:31:44.539Z",
  "ip": "227.44.85.229",
  "foo": "bar",
  "profile": {
    "about": "It ereoc afdamev mupehe igipom fulkakca ugo gik mop af vohula ahu dis iga moaci acval gapgijug. Ruk vewe pekgueba otcil eri ne am pecdo sugu cimser ra vu. Gohmam hu ivwob topzonuz kit sawed zu saguku ib hace ma ruj hakofibu niirja. Gura ilsusbu ihme batrer di fiwfig bu furuge duvoga tu ju hijeset betvi datkofom uwamodu tilkujop deg. Akaeh modinauva ela sidsofjor kizaviti giuvecub we hem deir ewdinow dimil mante zo.",
    "bio": "Gig pi desaviro za ludpogaw umkijih fi petep tu ogukuf ze harnat uwegi bawha toam rigti bojho. Vibirpek bugomu ter up zekuc odiuru wokur muohilo pa jebelta ivu gevhi biari uhejejbab na peljev bu jin. Eboetwej od oze bu gurhe wow tufan figab rovib lotlouja sem fuj fikogku wopza nuthu red vaetaana. Rofud tu pufguk cub fuc kew atzerir sucomekan kijginub sibnohame tiwge acojo jathaha lelevsa bu. Ela artuvli cuviw anpefud umeman ofulo sagah ul luftobken onoba jufu unu fallehdam ziwugidom ev."
  },
  "apiKey": "e5e7094e6bbfe63d7d7d2823a7aedd175e0b50527a7f7f955aac8447fd217569",
  "currency": {
    "code": "OMR",
    "name": "Oman Rial"
  }
}